agent_framework/__init__.py
agent_framework/qdrant/__init__.py
agent_framework_qdrant-0.0.0a1.dist-info/licenses/LICENSE
agent_framework_qdrant-0.0.0a1.dist-info/WHEEL
agent_framework_qdrant-0.0.0a1.dist-info/METADATA
agent_framework_qdrant-0.0.0a1.dist-info/RECORD
